scs/__init__.py
scs/handler.py
scs/constraint/__init__.py
scs/constraint/json.py
scs/constraint/one_of.py
scs/incremental_parse/__init__.py
scs/incremental_parse/string_match.py
scs/incremental_parse/json/__init__.py
scs/incremental_parse/json/parser.py
scs/incremental_parse/json/schema.py
sampling_constraints-0.0.18.dist-info/LICENSE
sampling_constraints-0.0.18.dist-info/METADATA
sampling_constraints-0.0.18.dist-info/WHEEL
sampling_constraints-0.0.18.dist-info/top_level.txt
sampling_constraints-0.0.18.dist-info/RECORD
