Metadata-Version: 2.1
Name: sampling-constraints
Version: 0.0.18
Summary: Library of incremental parsers used to force syntax constraints on next-token predictions during language model generation
Author-email: Isaac Rehg <isaacrehg@gmail.com>
Project-URL: Homepage, https://github.com/IsaacRe/Syntactically-Constrained-Sampling
Project-URL: Bug Tracker, https://github.com/IsaacRe/Syntactically-Constrained-Sampling/issues
Requires-Python: >=3.8
License-File: LICENSE
